RFKO_Xsuite/Rfko.py
RFKO_Xsuite/__init__.py
RFKO_Xsuite/bare_mach_setup.py
RFKO_Xsuite/check_functions.py
RFKO_Xsuite/line_setup.py
RFKO_Xsuite/macro.py
RFKO_Xsuite/phy_helper.py
RFKO_Xsuite/plotting1.py
RFKO_Xsuite/plotting2.py
RFKO_Xsuite/quad_ripples.py
RFKO_Xsuite/saving.py
RFKO_Xsuite/slowex_actions.py
RFKO_Xsuite/slowex_helper.py
RFKO_Xsuite/utility.py
RFKO_Xsuite/xsuite_actions.py
RFKO_Xsuite/xsuite_helper.py
RFKO_Xsuite-0.1.1.dev0.dist-info/METADATA
RFKO_Xsuite-0.1.1.dev0.dist-info/WHEEL
RFKO_Xsuite-0.1.1.dev0.dist-info/top_level.txt
RFKO_Xsuite-0.1.1.dev0.dist-info/RECORD
