Metadata-Version: 2.1
Name: RFKO_Xsuite
Version: 0.1.1.dev0
Summary: A package for wrapping up some funcitonalities from Xsuite
Home-page: https://gitlab.cern.ch/wscarpa/rfko_xsuite.git
Author: Wesley
Author-email: wesley.scarpa@cern.ch
License: MIT
Requires-Dist: cffi ==1.16.0
Requires-Dist: colorama ==0.4.6
Requires-Dist: contourpy ==1.2.1
Requires-Dist: cpymad ==1.16.3
Requires-Dist: cycler ==0.12.1
Requires-Dist: Cython ==3.0.10
Requires-Dist: exceptiongroup ==1.2.1
Requires-Dist: fonttools ==4.51.0
Requires-Dist: iniconfig ==2.0.0
Requires-Dist: kiwisolver ==1.4.5
Requires-Dist: lark ==1.1.9
Requires-Dist: matplotlib ==3.8.4
Requires-Dist: minrpc ==0.1.0
Requires-Dist: numpy ==1.26.4
Requires-Dist: packaging ==24.0
Requires-Dist: pandas ==2.2.2
Requires-Dist: pillow ==10.3.0
Requires-Dist: pluggy ==1.5.0
Requires-Dist: pycparser ==2.22
Requires-Dist: pyparsing ==3.1.2
Requires-Dist: pytest ==8.2.0
Requires-Dist: python-dateutil ==2.9.0.post0
Requires-Dist: pytz ==2024.1
Requires-Dist: scipy ==1.13.0
Requires-Dist: six ==1.16.0
Requires-Dist: tomli ==2.0.1
Requires-Dist: tqdm ==4.66.2
Requires-Dist: tzdata ==2024.1
Requires-Dist: xcoll ==0.3.6
Requires-Dist: xdeps ==0.5.7
Requires-Dist: xfields ==0.16.0
Requires-Dist: xobjects ==0.4.1
Requires-Dist: xpart ==0.18.2
Requires-Dist: xsuite ==0.8.0
Requires-Dist: xtrack ==0.59.0
